{
  "collections": [
    {
      "collectionName": "cwa-app-android",
      "folders": [
        {
          "startingFolderPath": "**/res/values-de/**",
          "sourceFilters": [
            "strings.xml",
            "contact_diary_strings.xml"
          ],
          "targetFolderPath": "../values-[langCode]"
        }
      ]
    }
  ],
  "defaultConfiguration": {
    "pseudoLocFolderPath": "../values-2Q",
    "oneQFolderPath": "../values-1Q",
    "targetFileNamingConvention": "[filename].[extension]"
  }
}